{
  "statusCode:": 200,
  "message": "Lists of respectives routes",
  "data":{
    "route_name": "Tapovan School Bannerghatta road, Jigani",
    "userId": "65f0725e45ef7a0dceace310",
    "busId": "661cb6ae6a1269c3ac83cf97",
    "route_coordinates": [
      {
        "lat": 25.55,
        "long": 75.55
      },
      {
        "lat": 25.55,
        "long": 75.55
      },
      {
        "lat": 25.55,
        "long": 75.55
      },
      {
        "lat": 25.55,
        "long": 75.55
      },
      {
        "lat": 25.55,
        "long": 75.55
      },
      {
        "lat": 25.55,
        "long": 75.55
      }
    ],
    "startLat": 25.55,
    "startLong": 25.55,
    "endLat": 25.55,
    "endLong": 25.55
  }
}
